<profile>

<ReportVersion>
<Version>2022.2</Version>
</ReportVersion>

<UserAssignments>
<unit>ns</unit>
<ProductFamily>zynq</ProductFamily>
<Part>xc7z010-clg400-1</Part>
<TopModelName>mmult_Pipeline_mmult0_mmult1</TopModelName>
<TargetClockPeriod>10.00</TargetClockPeriod>
<ClockUncertainty>2.70</ClockUncertainty>
<FlowTarget>vivado</FlowTarget>
</UserAssignments>

<PerformanceEstimates>
<PipelineType>no</PipelineType>
<SummaryOfTimingAnalysis>
<unit>ns</unit>
<EstimatedClockPeriod>6.923</EstimatedClockPeriod>
</SummaryOfTimingAnalysis>
<SummaryOfOverallLatency>
<unit>clock cycles</unit>
<Best-caseLatency>71</Best-caseLatency>
<Average-caseLatency>71</Average-caseLatency>
<Worst-caseLatency>71</Worst-caseLatency>
<Best-caseRealTimeLatency>0.710 us</Best-caseRealTimeLatency>
<Average-caseRealTimeLatency>0.710 us</Average-caseRealTimeLatency>
<Worst-caseRealTimeLatency>0.710 us</Worst-caseRealTimeLatency>
<Interval-min>71</Interval-min>
<Interval-max>71</Interval-max>
</SummaryOfOverallLatency>
<SummaryOfLoopLatency>
<mmult0_mmult1>
<Slack>7.30</Slack>
<TripCount>64</TripCount>
<Latency>69</Latency>
<AbsoluteTimeLatency>690</AbsoluteTimeLatency>
<PipelineII>1</PipelineII>
<PipelineDepth>7</PipelineDepth>
<InstanceList>
</InstanceList>
</mmult0_mmult1>
</SummaryOfLoopLatency>
</PerformanceEstimates>

<AreaEstimates>
<Resources>
<DSP>24</DSP>
<FF>2314</FF>
<LUT>965</LUT>
<BRAM_18K>0</BRAM_18K>
<URAM>0</URAM>
</Resources>
<AvailableResources>
<BRAM_18K>120</BRAM_18K>
<DSP>80</DSP>
<FF>35200</FF>
<LUT>17600</LUT>
<URAM>0</URAM>
</AvailableResources>
</AreaEstimates>

<InterfaceSummary>
<RtlPorts>
<name>ap_clk</name>
<Object>mmult_Pipeline_mmult0_mmult1</Object>
<Type>return value</Type>
<Scope></Scope>
<IOProtocol>ap_ctrl_hs</IOProtocol>
<IOConfig></IOConfig>
<Dir>in</Dir>
<Bits>1</Bits>
<Attribute>control</Attribute>
</RtlPorts>
<RtlPorts>
<name>ap_rst</name>
<Object>mmult_Pipeline_mmult0_mmult1</Object>
<Type>return value</Type>
<Scope></Scope>
<IOProtocol>ap_ctrl_hs</IOProtocol>
<IOConfig></IOConfig>
<Dir>in</Dir>
<Bits>1</Bits>
<Attribute>control</Attribute>
</RtlPorts>
<RtlPorts>
<name>ap_start</name>
<Object>mmult_Pipeline_mmult0_mmult1</Object>
<Type>return value</Type>
<Scope></Scope>
<IOProtocol>ap_ctrl_hs</IOProtocol>
<IOConfig></IOConfig>
<Dir>in</Dir>
<Bits>1</Bits>
<Attribute>control</Attribute>
</RtlPorts>
<RtlPorts>
<name>ap_done</name>
<Object>mmult_Pipeline_mmult0_mmult1</Object>
<Type>return value</Type>
<Scope></Scope>
<IOProtocol>ap_ctrl_hs</IOProtocol>
<IOConfig></IOConfig>
<Dir>out</Dir>
<Bits>1</Bits>
<Attribute>control</Attribute>
</RtlPorts>
<RtlPorts>
<name>ap_idle</name>
<Object>mmult_Pipeline_mmult0_mmult1</Object>
<Type>return value</Type>
<Scope></Scope>
<IOProtocol>ap_ctrl_hs</IOProtocol>
<IOConfig></IOConfig>
<Dir>out</Dir>
<Bits>1</Bits>
<Attribute>control</Attribute>
</RtlPorts>
<RtlPorts>
<name>ap_ready</name>
<Object>mmult_Pipeline_mmult0_mmult1</Object>
<Type>return value</Type>
<Scope></Scope>
<IOProtocol>ap_ctrl_hs</IOProtocol>
<IOConfig></IOConfig>
<Dir>out</Dir>
<Bits>1</Bits>
<Attribute>control</Attribute>
</RtlPorts>
<RtlPorts>
<name>a_buffer_address0</name>
<Object>a_buffer</Object>
<Type>array</Type>
<Scope></Scope>
<IOProtocol>ap_memory</IOProtocol>
<IOConfig></IOConfig>
<Dir>out</Dir>
<Bits>6</Bits>
<Attribute>address</Attribute>
</RtlPorts>
<RtlPorts>
<name>a_buffer_ce0</name>
<Object>a_buffer</Object>
<Type>array</Type>
<Scope></Scope>
<IOProtocol>ap_memory</IOProtocol>
<IOConfig></IOConfig>
<Dir>out</Dir>
<Bits>1</Bits>
<Attribute>control</Attribute>
</RtlPorts>
<RtlPorts>
<name>a_buffer_q0</name>
<Object>a_buffer</Object>
<Type>array</Type>
<Scope></Scope>
<IOProtocol>ap_memory</IOProtocol>
<IOConfig></IOConfig>
<Dir>in</Dir>
<Bits>32</Bits>
<Attribute>data</Attribute>
</RtlPorts>
<RtlPorts>
<name>a_buffer_address1</name>
<Object>a_buffer</Object>
<Type>array</Type>
<Scope></Scope>
<IOProtocol>ap_memory</IOProtocol>
<IOConfig></IOConfig>
<Dir>out</Dir>
<Bits>6</Bits>
<Attribute>address</Attribute>
</RtlPorts>
<RtlPorts>
<name>a_buffer_ce1</name>
<Object>a_buffer</Object>
<Type>array</Type>
<Scope></Scope>
<IOProtocol>ap_memory</IOProtocol>
<IOConfig></IOConfig>
<Dir>out</Dir>
<Bits>1</Bits>
<Attribute>control</Attribute>
</RtlPorts>
<RtlPorts>
<name>a_buffer_q1</name>
<Object>a_buffer</Object>
<Type>array</Type>
<Scope></Scope>
<IOProtocol>ap_memory</IOProtocol>
<IOConfig></IOConfig>
<Dir>in</Dir>
<Bits>32</Bits>
<Attribute>data</Attribute>
</RtlPorts>
<RtlPorts>
<name>a_buffer_address2</name>
<Object>a_buffer</Object>
<Type>array</Type>
<Scope></Scope>
<IOProtocol>ap_memory</IOProtocol>
<IOConfig></IOConfig>
<Dir>out</Dir>
<Bits>6</Bits>
<Attribute>address</Attribute>
</RtlPorts>
<RtlPorts>
<name>a_buffer_ce2</name>
<Object>a_buffer</Object>
<Type>array</Type>
<Scope></Scope>
<IOProtocol>ap_memory</IOProtocol>
<IOConfig></IOConfig>
<Dir>out</Dir>
<Bits>1</Bits>
<Attribute>control</Attribute>
</RtlPorts>
<RtlPorts>
<name>a_buffer_q2</name>
<Object>a_buffer</Object>
<Type>array</Type>
<Scope></Scope>
<IOProtocol>ap_memory</IOProtocol>
<IOConfig></IOConfig>
<Dir>in</Dir>
<Bits>32</Bits>
<Attribute>data</Attribute>
</RtlPorts>
<RtlPorts>
<name>a_buffer_address3</name>
<Object>a_buffer</Object>
<Type>array</Type>
<Scope></Scope>
<IOProtocol>ap_memory</IOProtocol>
<IOConfig></IOConfig>
<Dir>out</Dir>
<Bits>6</Bits>
<Attribute>address</Attribute>
</RtlPorts>
<RtlPorts>
<name>a_buffer_ce3</name>
<Object>a_buffer</Object>
<Type>array</Type>
<Scope></Scope>
<IOProtocol>ap_memory</IOProtocol>
<IOConfig></IOConfig>
<Dir>out</Dir>
<Bits>1</Bits>
<Attribute>control</Attribute>
</RtlPorts>
<RtlPorts>
<name>a_buffer_q3</name>
<Object>a_buffer</Object>
<Type>array</Type>
<Scope></Scope>
<IOProtocol>ap_memory</IOProtocol>
<IOConfig></IOConfig>
<Dir>in</Dir>
<Bits>32</Bits>
<Attribute>data</Attribute>
</RtlPorts>
<RtlPorts>
<name>a_buffer_address4</name>
<Object>a_buffer</Object>
<Type>array</Type>
<Scope></Scope>
<IOProtocol>ap_memory</IOProtocol>
<IOConfig></IOConfig>
<Dir>out</Dir>
<Bits>6</Bits>
<Attribute>address</Attribute>
</RtlPorts>
<RtlPorts>
<name>a_buffer_ce4</name>
<Object>a_buffer</Object>
<Type>array</Type>
<Scope></Scope>
<IOProtocol>ap_memory</IOProtocol>
<IOConfig></IOConfig>
<Dir>out</Dir>
<Bits>1</Bits>
<Attribute>control</Attribute>
</RtlPorts>
<RtlPorts>
<name>a_buffer_q4</name>
<Object>a_buffer</Object>
<Type>array</Type>
<Scope></Scope>
<IOProtocol>ap_memory</IOProtocol>
<IOConfig></IOConfig>
<Dir>in</Dir>
<Bits>32</Bits>
<Attribute>data</Attribute>
</RtlPorts>
<RtlPorts>
<name>a_buffer_address5</name>
<Object>a_buffer</Object>
<Type>array</Type>
<Scope></Scope>
<IOProtocol>ap_memory</IOProtocol>
<IOConfig></IOConfig>
<Dir>out</Dir>
<Bits>6</Bits>
<Attribute>address</Attribute>
</RtlPorts>
<RtlPorts>
<name>a_buffer_ce5</name>
<Object>a_buffer</Object>
<Type>array</Type>
<Scope></Scope>
<IOProtocol>ap_memory</IOProtocol>
<IOConfig></IOConfig>
<Dir>out</Dir>
<Bits>1</Bits>
<Attribute>control</Attribute>
</RtlPorts>
<RtlPorts>
<name>a_buffer_q5</name>
<Object>a_buffer</Object>
<Type>array</Type>
<Scope></Scope>
<IOProtocol>ap_memory</IOProtocol>
<IOConfig></IOConfig>
<Dir>in</Dir>
<Bits>32</Bits>
<Attribute>data</Attribute>
</RtlPorts>
<RtlPorts>
<name>a_buffer_address6</name>
<Object>a_buffer</Object>
<Type>array</Type>
<Scope></Scope>
<IOProtocol>ap_memory</IOProtocol>
<IOConfig></IOConfig>
<Dir>out</Dir>
<Bits>6</Bits>
<Attribute>address</Attribute>
</RtlPorts>
<RtlPorts>
<name>a_buffer_ce6</name>
<Object>a_buffer</Object>
<Type>array</Type>
<Scope></Scope>
<IOProtocol>ap_memory</IOProtocol>
<IOConfig></IOConfig>
<Dir>out</Dir>
<Bits>1</Bits>
<Attribute>control</Attribute>
</RtlPorts>
<RtlPorts>
<name>a_buffer_q6</name>
<Object>a_buffer</Object>
<Type>array</Type>
<Scope></Scope>
<IOProtocol>ap_memory</IOProtocol>
<IOConfig></IOConfig>
<Dir>in</Dir>
<Bits>32</Bits>
<Attribute>data</Attribute>
</RtlPorts>
<RtlPorts>
<name>a_buffer_address7</name>
<Object>a_buffer</Object>
<Type>array</Type>
<Scope></Scope>
<IOProtocol>ap_memory</IOProtocol>
<IOConfig></IOConfig>
<Dir>out</Dir>
<Bits>6</Bits>
<Attribute>address</Attribute>
</RtlPorts>
<RtlPorts>
<name>a_buffer_ce7</name>
<Object>a_buffer</Object>
<Type>array</Type>
<Scope></Scope>
<IOProtocol>ap_memory</IOProtocol>
<IOConfig></IOConfig>
<Dir>out</Dir>
<Bits>1</Bits>
<Attribute>control</Attribute>
</RtlPorts>
<RtlPorts>
<name>a_buffer_q7</name>
<Object>a_buffer</Object>
<Type>array</Type>
<Scope></Scope>
<IOProtocol>ap_memory</IOProtocol>
<IOConfig></IOConfig>
<Dir>in</Dir>
<Bits>32</Bits>
<Attribute>data</Attribute>
</RtlPorts>
<RtlPorts>
<name>b_buffer_address0</name>
<Object>b_buffer</Object>
<Type>array</Type>
<Scope></Scope>
<IOProtocol>ap_memory</IOProtocol>
<IOConfig></IOConfig>
<Dir>out</Dir>
<Bits>6</Bits>
<Attribute>address</Attribute>
</RtlPorts>
<RtlPorts>
<name>b_buffer_ce0</name>
<Object>b_buffer</Object>
<Type>array</Type>
<Scope></Scope>
<IOProtocol>ap_memory</IOProtocol>
<IOConfig></IOConfig>
<Dir>out</Dir>
<Bits>1</Bits>
<Attribute>control</Attribute>
</RtlPorts>
<RtlPorts>
<name>b_buffer_q0</name>
<Object>b_buffer</Object>
<Type>array</Type>
<Scope></Scope>
<IOProtocol>ap_memory</IOProtocol>
<IOConfig></IOConfig>
<Dir>in</Dir>
<Bits>32</Bits>
<Attribute>data</Attribute>
</RtlPorts>
<RtlPorts>
<name>b_buffer_address1</name>
<Object>b_buffer</Object>
<Type>array</Type>
<Scope></Scope>
<IOProtocol>ap_memory</IOProtocol>
<IOConfig></IOConfig>
<Dir>out</Dir>
<Bits>6</Bits>
<Attribute>address</Attribute>
</RtlPorts>
<RtlPorts>
<name>b_buffer_ce1</name>
<Object>b_buffer</Object>
<Type>array</Type>
<Scope></Scope>
<IOProtocol>ap_memory</IOProtocol>
<IOConfig></IOConfig>
<Dir>out</Dir>
<Bits>1</Bits>
<Attribute>control</Attribute>
</RtlPorts>
<RtlPorts>
<name>b_buffer_q1</name>
<Object>b_buffer</Object>
<Type>array</Type>
<Scope></Scope>
<IOProtocol>ap_memory</IOProtocol>
<IOConfig></IOConfig>
<Dir>in</Dir>
<Bits>32</Bits>
<Attribute>data</Attribute>
</RtlPorts>
<RtlPorts>
<name>b_buffer_address2</name>
<Object>b_buffer</Object>
<Type>array</Type>
<Scope></Scope>
<IOProtocol>ap_memory</IOProtocol>
<IOConfig></IOConfig>
<Dir>out</Dir>
<Bits>6</Bits>
<Attribute>address</Attribute>
</RtlPorts>
<RtlPorts>
<name>b_buffer_ce2</name>
<Object>b_buffer</Object>
<Type>array</Type>
<Scope></Scope>
<IOProtocol>ap_memory</IOProtocol>
<IOConfig></IOConfig>
<Dir>out</Dir>
<Bits>1</Bits>
<Attribute>control</Attribute>
</RtlPorts>
<RtlPorts>
<name>b_buffer_q2</name>
<Object>b_buffer</Object>
<Type>array</Type>
<Scope></Scope>
<IOProtocol>ap_memory</IOProtocol>
<IOConfig></IOConfig>
<Dir>in</Dir>
<Bits>32</Bits>
<Attribute>data</Attribute>
</RtlPorts>
<RtlPorts>
<name>b_buffer_address3</name>
<Object>b_buffer</Object>
<Type>array</Type>
<Scope></Scope>
<IOProtocol>ap_memory</IOProtocol>
<IOConfig></IOConfig>
<Dir>out</Dir>
<Bits>6</Bits>
<Attribute>address</Attribute>
</RtlPorts>
<RtlPorts>
<name>b_buffer_ce3</name>
<Object>b_buffer</Object>
<Type>array</Type>
<Scope></Scope>
<IOProtocol>ap_memory</IOProtocol>
<IOConfig></IOConfig>
<Dir>out</Dir>
<Bits>1</Bits>
<Attribute>control</Attribute>
</RtlPorts>
<RtlPorts>
<name>b_buffer_q3</name>
<Object>b_buffer</Object>
<Type>array</Type>
<Scope></Scope>
<IOProtocol>ap_memory</IOProtocol>
<IOConfig></IOConfig>
<Dir>in</Dir>
<Bits>32</Bits>
<Attribute>data</Attribute>
</RtlPorts>
<RtlPorts>
<name>b_buffer_address4</name>
<Object>b_buffer</Object>
<Type>array</Type>
<Scope></Scope>
<IOProtocol>ap_memory</IOProtocol>
<IOConfig></IOConfig>
<Dir>out</Dir>
<Bits>6</Bits>
<Attribute>address</Attribute>
</RtlPorts>
<RtlPorts>
<name>b_buffer_ce4</name>
<Object>b_buffer</Object>
<Type>array</Type>
<Scope></Scope>
<IOProtocol>ap_memory</IOProtocol>
<IOConfig></IOConfig>
<Dir>out</Dir>
<Bits>1</Bits>
<Attribute>control</Attribute>
</RtlPorts>
<RtlPorts>
<name>b_buffer_q4</name>
<Object>b_buffer</Object>
<Type>array</Type>
<Scope></Scope>
<IOProtocol>ap_memory</IOProtocol>
<IOConfig></IOConfig>
<Dir>in</Dir>
<Bits>32</Bits>
<Attribute>data</Attribute>
</RtlPorts>
<RtlPorts>
<name>b_buffer_address5</name>
<Object>b_buffer</Object>
<Type>array</Type>
<Scope></Scope>
<IOProtocol>ap_memory</IOProtocol>
<IOConfig></IOConfig>
<Dir>out</Dir>
<Bits>6</Bits>
<Attribute>address</Attribute>
</RtlPorts>
<RtlPorts>
<name>b_buffer_ce5</name>
<Object>b_buffer</Object>
<Type>array</Type>
<Scope></Scope>
<IOProtocol>ap_memory</IOProtocol>
<IOConfig></IOConfig>
<Dir>out</Dir>
<Bits>1</Bits>
<Attribute>control</Attribute>
</RtlPorts>
<RtlPorts>
<name>b_buffer_q5</name>
<Object>b_buffer</Object>
<Type>array</Type>
<Scope></Scope>
<IOProtocol>ap_memory</IOProtocol>
<IOConfig></IOConfig>
<Dir>in</Dir>
<Bits>32</Bits>
<Attribute>data</Attribute>
</RtlPorts>
<RtlPorts>
<name>b_buffer_address6</name>
<Object>b_buffer</Object>
<Type>array</Type>
<Scope></Scope>
<IOProtocol>ap_memory</IOProtocol>
<IOConfig></IOConfig>
<Dir>out</Dir>
<Bits>6</Bits>
<Attribute>address</Attribute>
</RtlPorts>
<RtlPorts>
<name>b_buffer_ce6</name>
<Object>b_buffer</Object>
<Type>array</Type>
<Scope></Scope>
<IOProtocol>ap_memory</IOProtocol>
<IOConfig></IOConfig>
<Dir>out</Dir>
<Bits>1</Bits>
<Attribute>control</Attribute>
</RtlPorts>
<RtlPorts>
<name>b_buffer_q6</name>
<Object>b_buffer</Object>
<Type>array</Type>
<Scope></Scope>
<IOProtocol>ap_memory</IOProtocol>
<IOConfig></IOConfig>
<Dir>in</Dir>
<Bits>32</Bits>
<Attribute>data</Attribute>
</RtlPorts>
<RtlPorts>
<name>b_buffer_address7</name>
<Object>b_buffer</Object>
<Type>array</Type>
<Scope></Scope>
<IOProtocol>ap_memory</IOProtocol>
<IOConfig></IOConfig>
<Dir>out</Dir>
<Bits>6</Bits>
<Attribute>address</Attribute>
</RtlPorts>
<RtlPorts>
<name>b_buffer_ce7</name>
<Object>b_buffer</Object>
<Type>array</Type>
<Scope></Scope>
<IOProtocol>ap_memory</IOProtocol>
<IOConfig></IOConfig>
<Dir>out</Dir>
<Bits>1</Bits>
<Attribute>control</Attribute>
</RtlPorts>
<RtlPorts>
<name>b_buffer_q7</name>
<Object>b_buffer</Object>
<Type>array</Type>
<Scope></Scope>
<IOProtocol>ap_memory</IOProtocol>
<IOConfig></IOConfig>
<Dir>in</Dir>
<Bits>32</Bits>
<Attribute>data</Attribute>
</RtlPorts>
<RtlPorts>
<name>c_buffer_address0</name>
<Object>c_buffer</Object>
<Type>array</Type>
<Scope></Scope>
<IOProtocol>ap_memory</IOProtocol>
<IOConfig></IOConfig>
<Dir>out</Dir>
<Bits>6</Bits>
<Attribute>address</Attribute>
</RtlPorts>
<RtlPorts>
<name>c_buffer_ce0</name>
<Object>c_buffer</Object>
<Type>array</Type>
<Scope></Scope>
<IOProtocol>ap_memory</IOProtocol>
<IOConfig></IOConfig>
<Dir>out</Dir>
<Bits>1</Bits>
<Attribute>control</Attribute>
</RtlPorts>
<RtlPorts>
<name>c_buffer_we0</name>
<Object>c_buffer</Object>
<Type>array</Type>
<Scope></Scope>
<IOProtocol>ap_memory</IOProtocol>
<IOConfig></IOConfig>
<Dir>out</Dir>
<Bits>1</Bits>
<Attribute>control</Attribute>
</RtlPorts>
<RtlPorts>
<name>c_buffer_d0</name>
<Object>c_buffer</Object>
<Type>array</Type>
<Scope></Scope>
<IOProtocol>ap_memory</IOProtocol>
<IOConfig></IOConfig>
<Dir>out</Dir>
<Bits>32</Bits>
<Attribute>data</Attribute>
</RtlPorts>
</InterfaceSummary>

</profile>
